data_exchange_tool/__init__.py
data_exchange_tool/admin/__init__.py
data_exchange_tool/admin/base_import_job.py
data_exchange_tool/admin/filters.py
data_exchange_tool/admin/messages.py
data_exchange_tool/apps.py
data_exchange_tool/data_exchange/__init__.py
data_exchange_tool/data_exchange/model_importer.py
data_exchange_tool/exceptions.py
data_exchange_tool/forms/__init__.py
data_exchange_tool/forms/import_file_form.py
data_exchange_tool/migrations/0001_initial.py
data_exchange_tool/migrations/__init__.py
data_exchange_tool/models/__init__.py
data_exchange_tool/models/import_job.py
data_exchange_tool/storage.py
data_exchange_tool/tasks/__init__.py
data_exchange_tool/tasks/preview_import_job.py
data_exchange_tool/tasks/process_import_job.py
data_exchange_tool/templates/import_preview_template.html
data_exchange_tool/templatetags/__init__.py
data_exchange_tool/templatetags/custom_filters.py
data_exchange_tool/utils.py
data_exchange_tool-0.1.8.dist-info/METADATA
data_exchange_tool-0.1.8.dist-info/WHEEL
data_exchange_tool-0.1.8.dist-info/RECORD
