Metadata-Version: 2.3
Name: data_exchange_tool
Version: 0.1.8
Summary: Tool for django models import
Author: Toni Caparrós García
Author-email: tonicapagarcia@gmail.com
Requires-Python: >=3.11,<4.0
Classifier: Programming Language :: Python :: 3
Classifier: Programming Language :: Python :: 3.11
Classifier: Programming Language :: Python :: 3.12
Classifier: Programming Language :: Python :: 3.13
Requires-Dist: boto3 (>=1.26.37)
Requires-Dist: celery (>=5.0)
Requires-Dist: django (>=3.0)
Requires-Dist: django-storages (>=1.12.3)
Requires-Dist: polars (>=1.32.0,<2.0.0)
Requires-Dist: python-decouple (>=3.8,<4.0)
Requires-Dist: redis (>=6.2.0)
